LICENSE.md
MANIFEST.in
README.rst
setup.py
dupfileremover/__init__.py
dupfileremover/command_line.py
dupfileremover/duplicateChecker.py
dupfileremover.egg-info/PKG-INFO
dupfileremover.egg-info/SOURCES.txt
dupfileremover.egg-info/dependency_links.txt
dupfileremover.egg-info/entry_points.txt
dupfileremover.egg-info/requires.txt
dupfileremover.egg-info/top_level.txt