Metadata-Version: 1.0
Name: dupfileremover
Version: 0.2.2
Summary: A command line utility that helps you find and remove duplicate files
Home-page: http://github.com/kpeterstech/dupfileremover
Author: Kit Peterson
Author-email: kpeterstech@gmail.com
License: MIT
Platform: UNKNOWN
